custom_email_user/__init__.py
custom_email_user/admin.py
custom_email_user/apps.py
custom_email_user/forms.py
custom_email_user/models.py
custom_email_user/tests.py
custom_email_user/views.py
custom_email_user/migrations/__init__.py
django_custom_email_user-0.1.dist-info/LICENSE
django_custom_email_user-0.1.dist-info/METADATA
django_custom_email_user-0.1.dist-info/WHEEL
django_custom_email_user-0.1.dist-info/top_level.txt
django_custom_email_user-0.1.dist-info/RECORD
