Metadata-Version: 2.1
Name: django-custom-email-user
Version: 0.1
Summary: Modify Django default User to use email as unique identifier
Home-page: https://github.com/garyburgmann/django-custom-email-user
Author: Gary Burgmann
Author-email: garyburgmann@gmail.com
License: UNKNOWN
Platform: UNKNOWN
Classifier: Programming Language :: Python :: 3
Classifier: License :: OSI Approved :: MIT License
Classifier: Operating System :: OS Independent
